{
  "project_info": {
    "project_number": "771916086138",
    "project_id": "pizza-house-4319d",
    "storage_bucket": "pizza-house-4319d.appspot.com"
  },
  "client": [
    {
      "client_info": {
        "mobilesdk_app_id": "1:771916086138:android:42688f579b2caaf773b4c3",
        "android_client_info": {
          "package_name": "com.example.pizza_house"
        }
      },
      "oauth_client": [],
      "api_key": [
        {
          "current_key": "AIzaSyAGf45vkYJgg0jXTJv9YFYCywvflaFltbE"
        }
      ],
      "services": {
        "appinvite_service": {
          "other_platform_oauth_client": []
        }
      }
    }
  ],
  "configuration_version": "1"
}